MANIFEST.in
README.rst
setup.py
udbnn/__init__.py
udbnn/__version__.py
udbnn/clear.py
udbnn/fit.py
udbnn/model.py
udbnn/udbnn.py
udbnn.egg-info/PKG-INFO
udbnn.egg-info/SOURCES.txt
udbnn.egg-info/dependency_links.txt
udbnn.egg-info/requires.txt
udbnn.egg-info/top_level.txt
udbnn/utils/__init__.py
udbnn/utils/dataset.py
udbnn/utils/get_batch_sizes.py
udbnn/utils/is_cached.py
udbnn/utils/load_settings.py
udbnn/utils/path.py
udbnn/utils/ungzip.py