Metadata-Version: 2.1
Name: udbnn
Version: 0.0.6
Summary: Experiment to determine whetever a large batch-size can be helpful with extremely umbalanced datasets.
Home-page: https://github.com/LucaCappelletti94/udbnn
Author: Luca Cappelletti
Author-email: cappelletti.luca94@gmail.com
License: MIT
Platform: UNKNOWN
Classifier: Development Status :: 3 - Alpha
Classifier: License :: OSI Approved :: MIT License
Classifier: Programming Language :: Python :: 3
Provides-Extra: test
